ures_visual/__init__.py
ures_visual/backend/__init__.py
ures_visual/backend/__pycache__/__init__.cpython-312.pyc
ures_visual/backend/__pycache__/core.cpython-312.pyc
ures_visual/backend/__pycache__/deps.cpython-312.pyc
ures_visual/backend/__pycache__/interactive.cpython-312.pyc
ures_visual/backend/__pycache__/research.cpython-312.pyc
ures_visual/backend/core.py
ures_visual/backend/deps.py
ures_visual/backend/interactive.py
ures_visual/backend/research.py
ures_visual/ml.py
ures_visual-1.0.3.dist-info/LICENSE
ures_visual-1.0.3.dist-info/METADATA
ures_visual-1.0.3.dist-info/WHEEL
ures_visual-1.0.3.dist-info/RECORD
