Metadata-Version: 2.3
Name: ures-visual
Version: 1.0.3
Summary: A comprehensive, multi-backend visualization library designed for scientific research, data analysis, and machine learning, built on Polars DataFrames with matplotlib/seaborn, plotly, and HoloViews backends.
License: MIT
Keywords: utilization,Research Tool,Python,visualization,data analysis,machine learning,data science
Author: stone
Author-email: github@stone-bo.com
Requires-Python: >=3.11
Classifier: Development Status :: 2 - Pre-Alpha
Classifier: Intended Audience :: Developers
Classifier: License :: OSI Approved :: MIT License
Classifier: Programming Language :: Python :: 3.11
Classifier: Programming Language :: Python :: 3.12
Classifier: Programming Language :: Python :: Implementation :: PyPy
Classifier: Topic :: Software Development :: Libraries :: Python Modules
Classifier: Topic :: Utilities
Classifier: Topic :: Scientific/Engineering :: Visualization
Classifier: Topic :: Scientific/Engineering :: Information Analysis
Requires-Dist: bokeh (>=3.7.3,<4.0.0)
Requires-Dist: holoviews (>=1.21.0,<2.0.0)
Requires-Dist: kaleido (>=1.0.0,<2.0.0)
Requires-Dist: matplotlib (>=3.10.5,<4.0.0)
Requires-Dist: numpy (>=2.2,<2.3)
Requires-Dist: plotly (>=6.2.0,<7.0.0)
Requires-Dist: polars (>=1.32.2,<2.0.0)
Requires-Dist: psutil (>=7.0.0,<8.0.0)
Requires-Dist: pyarrow (>=21.0.0,<22.0.0)
Requires-Dist: scikit-learn (>=1.7.1,<2.0.0)
Requires-Dist: scipy (>=1.16.1,<2.0.0)
Requires-Dist: seaborn (>=0.13.2,<0.14.0)
Requires-Dist: statsmodels (>=0.14.5,<0.15.0)
Requires-Dist: statsmodels (>=0.14.5,<0.15.0)
